pakfortabletocolumn/__init__.py
pakfortabletocolumn/__main__.py
pakfortabletocolumn/tabletocolumn.py
pakfortabletocolumn-0.1.4.dist-info/METADATA
pakfortabletocolumn-0.1.4.dist-info/WHEEL
pakfortabletocolumn-0.1.4.dist-info/entry_points.txt
pakfortabletocolumn-0.1.4.dist-info/top_level.txt
pakfortabletocolumn-0.1.4.dist-info/RECORD
