Metadata-Version: 2.1
Name: pakfortabletocolumn
Version: 0.1.4
Summary: table to column
Home-page: https://github.com/susaninsl/pakfortabletocolumn
Author: Sviat
Author-email: susaninsl@gmail.com
License: BSD 2-clause
Platform: UNKNOWN
Classifier: Development Status :: 1 - Planning
Classifier: License :: OSI Approved :: BSD License
Classifier: Programming Language :: Python :: 3
Classifier: Programming Language :: Python :: 3.4
Classifier: Programming Language :: Python :: 3.5
Requires-Dist: xlrd
Requires-Dist: xlwt
Requires-Dist: argparse
Requires-Dist: xlutils
